sgx_dcap_quote_verify_python-0.0.3.dist-info/METADATA
sgx_dcap_quote_verify_python-0.0.3.dist-info/WHEEL
sgx_dcap_quote_verify_python-0.0.3.dist-info/RECORD
sgx_dcap_quote_verify_python-0.0.3.dist-info/top_level.txt
sgx_dcap_quote_verify/_core.pyi
sgx_dcap_quote_verify/py.typed
sgx_dcap_quote_verify/__init__.py
sgx_dcap_quote_verify/_core_wrapper.py
sgx_dcap_quote_verify/_core.cpython-311-x86_64-linux-gnu.so
