Metadata-Version: 2.1
Name: sgx-dcap-quote-verify-python
Version: 0.0.3
Summary: Python package to verify Intel SGX ECDSA-based quotes
Author: Mithril Security
Author-email: contact@mithrilsecurity.io
License: Apache-2.0
Project-URL: Source, https://github.com/mithril-security/sgx-dcap-quote-verify-python
Requires-Python: >=3.7
Provides-Extra: test
